Workbook

Sheet Portada
B2: dovo | Modelo Financiero de Inversionista
B3: Fitness para DUOS · dovofit.com · Pre-seed · Mexico (MXN)
B5: SENSIBILIDAD #1 = CHURN. La racha del duo es la tesis: si el churn baja de ~12% a ~5%, el LTV y el LTV:CAC se multiplican. Es la palanca que mas mueve el valor del negocio.
B7: Unidad de negocio
B8: 1 DUO = 2 personas = 1 suscripcion
B9: Free (primeros 200 duos) -> Pro ($99 MXN/mes/duo) -> Premium
B10: Margen bruto objetivo > 80%
B12: Hito | C12: Conservador | D12: Base | E12: Agresivo
B13: MRR M12 | C13: =Hitos!C5 -> 1424.9363 | D13: =Hitos!D5 -> 7076.1979 | E13: =Hitos!E5 -> 29560.652
B14: MRR M24 | C14: =Hitos!C6 -> 6318.9015 | D14: =Hitos!D6 -> 32205.693 | E14: =Hitos!E6 -> 141072.23
B15: MRR M36 | C15: =Hitos!C7 -> 18039.405 | D15: =Hitos!D7 -> 108742.86 | E15: =Hitos!E7 -> 545243.75
B16: ARR M36 | C16: =Hitos!C8 -> 216472.86 | D16: =Hitos!D8 -> 1304914.4 | E16: =Hitos!E8 -> 6542925
B17: LTV:CAC (Base) | D17: ='Unit Economics'!C10 -> 350
B18: Payback (Base) | D18: ='Unit Economics'!C11 -> 906.4375
B20: Leyenda:
B21: Celda EDITABLE (input)
B22: Formula calculada
B23: Link a otra hoja
B25: Todas las cifras en MXN. Mercado e hitos = SUPUESTOS pre-seed, no garantias.

Sheet Supuestos
B2: Supuestos (celdas amarillas = editables)
B3: Cambia las celdas amarillas y todo el modelo se recalcula. Sensibilidad #1 = Churn mensual. Adquisicion (nuevos duos M1 y crecimiento MoM) esta calibrada para reproducir los hitos de MRR objetivo; conversion, churn, precio y costos son palancas de negocio editables.
B5: Variable | C5: Conservador | D5: Base | E5: Agresivo
B6: Nuevos duos / mes (M1) | C6: 33 | D6: 47 | E6: 87 | G6: Adquisicion inicial mes 1 (calibrado a hitos de MRR)
B7: Crecimiento MoM (nuevos) | C7: 0.08 | D7: 0.1 | E7: 0.115 | G7: Crecimiento mensual de los nuevos duos (calibrado a hitos)
B8: Conversion Free -> Pro | C8: 0.06 | D8: 0.12 | E8: 0.2 | G8: % de duos activos que pagan
B9: Churn mensual (pagos) | C9: 0.08 | D9: 0.05 | E9: 0.035 | G9: SENSIBILIDAD #1: la racha del duo
B10: Costo variable / duo / mes | C10: 25 | D10: 20 | E10: 15 | G10: Infra, pasarela, soporte por duo de pago
B11: CAC por duo | C11: 350 | D11: 250 | E11: 180 | G11: Costo de adquisicion por duo
B12: Precio / duo / mes | C12: 99 | D12: 99 | E12: 99 | G12: Plan Pro mensual por duo
B13: Mix anual (descuento) | C13: 0.1 | D13: 0.2 | E13: 0.3 | G13: % de pagos en plan anual con descuento
B14: Free iniciales (no pagan) | C14: 200 | D14: 200 | E14: 200 | G14: Primeros 200 duos en Free
B15: Descuento del plan anual | C15: 0.15 | D15: 0.15 | E15: 0.15 | G15: Descuento aplicado al precio anual
B17: ARPU efectivo = precio * (1 - mix_anual * descuento_anual). El plan anual reduce el ingreso mensual promedio por el descuento.

Sheet Proyeccion
A1: Proyeccion a 36 meses por escenario
A2: Todo referencia la hoja Supuestos. ARPU efectivo ajustado por mix anual. Free no paga; conversion aplica sobre activos por arriba de los Free iniciales.
A4: Escenario: Conservador
A5: Mes | B5: Nuevos duos | C5: Duos activos | D5: Duos de pago | E5: ARPU efectivo | F5: MRR | G5: ARR | H5: Costo var. total | I5: Margen bruto | J5: Margen %
A6: 1 | B6: =Supuestos!C6 -> 33 | C6: =B6 -> 33 | D6: =MAX(0,C6-Supuestos!C14)*Supuestos!C8 -> 0 | E6: =Supuestos!C12*(1-Supuestos!C13*Supuestos!C15) -> 97.515 | F6: =D6*E6 -> 0 | G6: =F6*12 -> 0 | H6: =D6*Supuestos!C10 -> 0 | I6: =F6-H6 -> 0 | J6: =IF(F6=0,0,I6/F6) -> 0
A7: 2 | B7: =B6*(1+Supuestos!C7) -> 35.64 | C7: =C6*(1-Supuestos!C9)+B7 -> 66 | D7: =MAX(0,C7-Supuestos!C14)*Supuestos!C8 -> 0 | E7: =Supuestos!C12*(1-Supuestos!C13*Supuestos!C15) -> 97.515 | F7: =D7*E7 -> 0 | G7: =F7*12 -> 0 | H7: =D7*Supuestos!C10 -> 0 | I7: =F7-H7 -> 0 | J7: =IF(F7=0,0,I7/F7) -> 0
A8: 3 | B8: =B7*(1+Supuestos!C7) -> 38.4912 | C8: =C7*(1-Supuestos!C9)+B8 -> 99.2112 | D8: =MAX(0,C8-Supuestos!C14)*Supuestos!C8 -> 0 | E8: =Supuestos!C12*(1-Supuestos!C13*Supuestos!C15) -> 97.515 | F8: =D8*E8 -> 0 | G8: =F8*12 -> 0 | H8: =D8*Supuestos!C10 -> 0 | I8: =F8-H8 -> 0 | J8: =IF(F8=0,0,I8/F8) -> 0
A9: 4 | B9: =B8*(1+Supuestos!C7) -> 41.570496 | C9: =C8*(1-Supuestos!C9)+B9 -> 132.8448 | D9: =MAX(0,C9-Supuestos!C14)*Supuestos!C8 -> 0 | E9: =Supuestos!C12*(1-Supuestos!C13*Supuestos!C15) -> 97.515 | F9: =D9*E9 -> 0 | G9: =F9*12 -> 0 | H9: =D9*Supuestos!C10 -> 0 | I9: =F9-H9 -> 0 | J9: =IF(F9=0,0,I9/F9) -> 0
A10: 5 | B10: =B9*(1+Supuestos!C7) -> 44.896136 | C10: =C9*(1-Supuestos!C9)+B10 -> 167.11335 | D10: =MAX(0,C10-Supuestos!C14)*Supuestos!C8 -> 0 | E10: =Supuestos!C12*(1-Supuestos!C13*Supuestos!C15) -> 97.515 | F10: =D10*E10 -> 0 | G10: =F10*12 -> 0 | H10: =D10*Supuestos!C10 -> 0 | I10: =F10-H10 -> 0 | J10: =IF(F10=0,0,I10/F10) -> 0
A11: 6 | B11: =B10*(1+Supuestos!C7) -> 48.487827 | C11: =C10*(1-Supuestos!C9)+B11 -> 202.23211 | D11: =MAX(0,C11-Supuestos!C14)*Supuestos!C8 -> 0.1339266 | E11: =Supuestos!C12*(1-Supuestos!C13*Supuestos!C15) -> 97.515 | F11: =D11*E11 -> 13.059853 | G11: =F11*12 -> 156.71823 | H11: =D11*Supuestos!C10 -> 3.3481651 | I11: =F11-H11 -> 9.7116877 | J11: =IF(F11=0,0,I11/F11) -> 0.74362919
A12: 7 | B12: =B11*(1+Supuestos!C7) -> 52.366853 | C12: =C11*(1-Supuestos!C9)+B12 -> 238.42039 | D12: =MAX(0,C12-Supuestos!C14)*Supuestos!C8 -> 2.3052236 | E12: =Supuestos!C12*(1-Supuestos!C13*Supuestos!C15) -> 97.515 | F12: =D12*E12 -> 224.79388 | G12: =F12*12 -> 2697.5266 | H12: =D12*Supuestos!C10 -> 57.630591 | I12: =F12-H12 -> 167.16329 | J12: =IF(F12=0,0,I12/F12) -> 0.74362919
A13: 8 | B13: =B12*(1+Supuestos!C7) -> 56.556201 | C13: =C12*(1-Supuestos!C9)+B13 -> 275.90296 | D13: =MAX(0,C13-Supuestos!C14)*Supuestos!C8 -> 4.5541778 | E13: =Supuestos!C12*(1-Supuestos!C13*Supuestos!C15) -> 97.515 | F13: =D13*E13 -> 444.10065 | G13: =F13*12 -> 5329.2078 | H13: =D13*Supuestos!C10 -> 113.85444 | I13: =F13-H13 -> 330.2462 | J13: =IF(F13=0,0,I13/F13) -> 0.74362919
A14: 9 | B14: =B13*(1+Supuestos!C7) -> 61.080697 | C14: =C13*(1-Supuestos!C9)+B14 -> 314.91142 | D14: =MAX(0,C14-Supuestos!C14)*Supuestos!C8 -> 6.8946854 | E14: =Supuestos!C12*(1-Supuestos!C13*Supuestos!C15) -> 97.515 | F14: =D14*E14 -> 672.33525 | G14: =F14*12 -> 8068.0229 | H14: =D14*Supuestos!C10 -> 172.36713 | I14: =F14-H14 -> 499.96811 | J14: =IF(F14=0,0,I14/F14) -> 0.74362919
A15: 10 | B15: =B14*(1+Supuestos!C7) -> 65.967153 | C15: =C14*(1-Supuestos!C9)+B15 -> 355.68566 | D15: =MAX(0,C15-Supuestos!C14)*Supuestos!C8 -> 9.3411397 | E15: =Supuestos!C12*(1-Supuestos!C13*Supuestos!C15) -> 97.515 | F15: =D15*E15 -> 910.90124 | G15: =F15*12 -> 10930.815 | H15: =D15*Supuestos!C10 -> 233.52849 | I15: =F15-H15 -> 677.37275 | J15: =IF(F15=0,0,I15/F15) -> 0.74362919
A16: 11 | B16: =B15*(1+Supuestos!C7) -> 71.244525 | C16: =C15*(1-Supuestos!C9)+B16 -> 398.47533 | D16: =MAX(0,C16-Supuestos!C14)*Supuestos!C8 -> 11.90852 | E16: =Supuestos!C12*(1-Supuestos!C13*Supuestos!C15) -> 97.515 | F16: =D16*E16 -> 1161.2593 | G16: =F16*12 -> 13935.112 | H16: =D16*Supuestos!C10 -> 297.713 | I16: =F16-H16 -> 863.54633 | J16: =IF(F16=0,0,I16/F16) -> 0.74362919
A17: 12 | B17: =B16*(1+Supuestos!C7) -> 76.944087 | C17: =C16*(1-Supuestos!C9)+B17 -> 443.54139 | D17: =MAX(0,C17-Supuestos!C14)*Supuestos!C8 -> 14.612484 | E17: =Supuestos!C12*(1-Supuestos!C13*Supuestos!C15) -> 97.515 | F17: =D17*E17 -> 1424.9363 | G17: =F17*12 -> 17099.236 | H17: =D17*Supuestos!C10 -> 365.31209 | I17: =F17-H17 -> 1059.6243 | J17: =IF(F17=0,0,I17/F17) -> 0.74362919
A18: 13 | B18: =B17*(1+Supuestos!C7) -> 83.099614 | C18: =C17*(1-Supuestos!C9)+B18 -> 491.1577 | D18: =MAX(0,C18-Supuestos!C14)*Supuestos!C8 -> 17.469462 | E18: =Supuestos!C12*(1-Supuestos!C13*Supuestos!C15) -> 97.515 | F18: =D18*E18 -> 1703.5346 | G18: =F18*12 -> 20442.415 | H18: =D18*Supuestos!C10 -> 436.73654 | I18: =F18-H18 -> 1266.798 | J18: =IF(F18=0,0,I18/F18) -> 0.74362919
A19: 14 | B19: =B18*(1+Supuestos!C7) -> 89.747583 | C19: =C18*(1-Supuestos!C9)+B19 -> 541.61266 | D19: =MAX(0,C19-Supuestos!C14)*Supuestos!C8 -> 20.49676 | E19: =Supuestos!C12*(1-Supuestos!C13*Supuestos!C15) -> 97.515 | F19: =D19*E19 -> 1998.7415 | G19: =F19*12 -> 23984.898 | H19: =D19*Supuestos!C10 -> 512.419 | I19: =F19-H19 -> 1486.3225 | J19: =IF(F19=0,0,I19/F19) -> 0.74362919
A20: 15 | B20: =B19*(1+Supuestos!C7) -> 96.92739 | C20: =C19*(1-Supuestos!C9)+B20 -> 595.21104 | D20: =MAX(0,C20-Supuestos!C14)*Supuestos!C8 -> 23.712662 | E20: =Supuestos!C12*(1-Supuestos!C13*Supuestos!C15) -> 97.515 | F20: =D20*E20 -> 2312.3403 | G20: =F20*12 -> 27748.083 | H20: =D20*Supuestos!C10 -> 592.81656 | I20: =F20-H20 -> 1719.5237 | J20: =IF(F20=0,0,I20/F20) -> 0.74362919
A21: 16 | B21: =B20*(1+Supuestos!C7) -> 104.68158 | C21: =C20*(1-Supuestos!C9)+B21 -> 652.27574 | D21: =MAX(0,C21-Supuestos!C14)*Supuestos!C8 -> 27.136544 | E21: =Supuestos!C12*(1-Supuestos!C13*Supuestos!C15) -> 97.515 | F21: =D21*E21 -> 2646.2201 | G21: =F21*12 -> 31754.641 | H21: =D21*Supuestos!C10 -> 678.41361 | I21: =F21-H21 -> 1967.8065 | J21: =IF(F21=0,0,I21/F21) -> 0.74362919
A22: 17 | B22: =B21*(1+Supuestos!C7) -> 113.05611 | C22: =C21*(1-Supuestos!C9)+B22 -> 713.14979 | D22: =MAX(0,C22-Supuestos!C14)*Supuestos!C8 -> 30.788987 | E22: =Supuestos!C12*(1-Supuestos!C13*Supuestos!C15) -> 97.515 | F22: =D22*E22 -> 3002.3881 | G22: =F22*12 -> 36028.657 | H22: =D22*Supuestos!C10 -> 769.72468 | I22: =F22-H22 -> 2232.6634 | J22: =IF(F22=0,0,I22/F22) -> 0.74362919
A23: 18 | B23: =B22*(1+Supuestos!C7) -> 122.1006 | C23: =C22*(1-Supuestos!C9)+B23 -> 778.1984 | D23: =MAX(0,C23-Supuestos!C14)*Supuestos!C8 -> 34.691904 | E23: =Supuestos!C12*(1-Supuestos!C13*Supuestos!C15) -> 97.515 | F23: =D23*E23 -> 3382.981 | G23: =F23*12 -> 40595.772 | H23: =D23*Supuestos!C10 -> 867.2976 | I23: =F23-H23 -> 2515.6834 | J23: =IF(F23=0,0,I23/F23) -> 0.74362919
A24: 19 | B24: =B23*(1+Supuestos!C7) -> 131.86864 | C24: =C23*(1-Supuestos!C9)+B24 -> 847.81117 | D24: =MAX(0,C24-Supuestos!C14)*Supuestos!C8 -> 38.86867 | E24: =Supuestos!C12*(1-Supuestos!C13*Supuestos!C15) -> 97.515 | F24: =D24*E24 -> 3790.2784 | G24: =F24*12 -> 45483.341 | H24: =D24*Supuestos!C10 -> 971.71676 | I24: =F24-H24 -> 2818.5616 | J24: =IF(F24=0,0,I24/F24) -> 0.74362919
A25: 20 | B25: =B24*(1+Supuestos!C7) -> 142.41813 | C25: =C24*(1-Supuestos!C9)+B25 -> 922.40441 | D25: =MAX(0,C25-Supuestos!C14)*Supuestos!C8 -> 43.344265 | E25: =Supuestos!C12*(1-Supuestos!C13*Supuestos!C15) -> 97.515 | F25: =D25*E25 -> 4226.716 | G25: =F25*12 -> 50720.592 | H25: =D25*Supuestos!C10 -> 1083.6066 | I25: =F25-H25 -> 3143.1094 | J25: =IF(F25=0,0,I25/F25) -> 0.74362919
A26: 21 | B26: =B25*(1+Supuestos!C7) -> 153.81159 | C26: =C25*(1-Supuestos!C9)+B26 -> 1002.4236 | D26: =MAX(0,C26-Supuestos!C14)*Supuestos!C8 -> 48.145419 | E26: =Supuestos!C12*(1-Supuestos!C13*Supuestos!C15) -> 97.515 | F26: =D26*E26 -> 4694.9005 | G26: =F26*12 -> 56338.806 | H26: =D26*Supuestos!C10 -> 1203.6355 | I26: =F26-H26 -> 3491.265 | J26: =IF(F26=0,0,I26/F26) -> 0.74362919
A27: 22 | B27: =B26*(1+Supuestos!C7) -> 166.11651 | C27: =C26*(1-Supuestos!C9)+B27 -> 1088.3463 | D27: =MAX(0,C27-Supuestos!C14)*Supuestos!C8 -> 53.300776 | E27: =Supuestos!C12*(1-Supuestos!C13*Supuestos!C15) -> 97.515 | F27: =D27*E27 -> 5197.6252 | G27: =F27*12 -> 62371.502 | H27: =D27*Supuestos!C10 -> 1332.5194 | I27: =F27-H27 -> 3865.1058 | J27: =IF(F27=0,0,I27/F27) -> 0.74362919
A28: 23 | B28: =B27*(1+Supuestos!C7) -> 179.40583 | C28: =C27*(1-Supuestos!C9)+B28 -> 1180.6844 | D28: =MAX(0,C28-Supuestos!C14)*Supuestos!C8 -> 58.841064 | E28: =Supuestos!C12*(1-Supuestos!C13*Supuestos!C15) -> 97.515 | F28: =D28*E28 -> 5737.8863 | G28: =F28*12 -> 68854.636 | H28: =D28*Supuestos!C10 -> 1471.0266 | I28: =F28-H28 -> 4266.8597 | J28: =IF(F28=0,0,I28/F28) -> 0.74362919
A29: 24 | B29: =B28*(1+Supuestos!C7) -> 193.7583 | C29: =C28*(1-Supuestos!C9)+B29 -> 1279.9879 | D29: =MAX(0,C29-Supuestos!C14)*Supuestos!C8 -> 64.799277 | E29: =Supuestos!C12*(1-Supuestos!C13*Supuestos!C15) -> 97.515 | F29: =D29*E29 -> 6318.9015 | G29: =F29*12 -> 75826.818 | H29: =D29*Supuestos!C10 -> 1619.9819 | I29: =F29-H29 -> 4698.9196 | J29: =IF(F29=0,0,I29/F29) -> 0.74362919
A30: 25 | B30: =B29*(1+Supuestos!C7) -> 209.25896 | C30: =C29*(1-Supuestos!C9)+B30 -> 1386.8479 | D30: =MAX(0,C30-Supuestos!C14)*Supuestos!C8 -> 71.210873 | E30: =Supuestos!C12*(1-Supuestos!C13*Supuestos!C15) -> 97.515 | F30: =D30*E30 -> 6944.1282 | G30: =F30*12 -> 83329.539 | H30: =D30*Supuestos!C10 -> 1780.2718 | I30: =F30-H30 -> 5163.8564 | J30: =IF(F30=0,0,I30/F30) -> 0.74362919
A31: 26 | B31: =B30*(1+Supuestos!C7) -> 225.99968 | C31: =C30*(1-Supuestos!C9)+B31 -> 1501.8997 | D31: =MAX(0,C31-Supuestos!C14)*Supuestos!C8 -> 78.113984 | E31: =Supuestos!C12*(1-Supuestos!C13*Supuestos!C15) -> 97.515 | F31: =D31*E31 -> 7617.2851 | G31: =F31*12 -> 91407.421 | H31: =D31*Supuestos!C10 -> 1952.8496 | I31: =F31-H31 -> 5664.4355 | J31: =IF(F31=0,0,I31/F31) -> 0.74362919
A32: 27 | B32: =B31*(1+Supuestos!C7) -> 244.07966 | C32: =C31*(1-Supuestos!C9)+B32 -> 1625.8274 | D32: =MAX(0,C32-Supuestos!C14)*Supuestos!C8 -> 85.549644 | E32: =Supuestos!C12*(1-Supuestos!C13*Supuestos!C15) -> 97.515 | F32: =D32*E32 -> 8342.3736 | G32: =F32*12 -> 100108.48 | H32: =D32*Supuestos!C10 -> 2138.7411 | I32: =F32-H32 -> 6203.6325 | J32: =IF(F32=0,0,I32/F32) -> 0.74362919
A33: 28 | B33: =B32*(1+Supuestos!C7) -> 263.60603 | C33: =C32*(1-Supuestos!C9)+B33 -> 1759.3672 | D33: =MAX(0,C33-Supuestos!C14)*Supuestos!C8 -> 93.562034 | E33: =Supuestos!C12*(1-Supuestos!C13*Supuestos!C15) -> 97.515 | F33: =D33*E33 -> 9123.7018 | G33: =F33*12 -> 109484.42 | H33: =D33*Supuestos!C10 -> 2339.0509 | I33: =F33-H33 -> 6784.6509 | J33: =IF(F33=0,0,I33/F33) -> 0.74362919
A34: 29 | B34: =B33*(1+Supuestos!C7) -> 284.69451 | C34: =C33*(1-Supuestos!C9)+B34 -> 1903.3124 | D34: =MAX(0,C34-Supuestos!C14)*Supuestos!C8 -> 102.19874 | E34: =Supuestos!C12*(1-Supuestos!C13*Supuestos!C15) -> 97.515 | F34: =D34*E34 -> 9965.9104 | G34: =F34*12 -> 119590.92 | H34: =D34*Supuestos!C10 -> 2554.9686 | I34: =F34-H34 -> 7410.9418 | J34: =IF(F34=0,0,I34/F34) -> 0.74362919
A35: 30 | B35: =B34*(1+Supuestos!C7) -> 307.47007 | C35: =C34*(1-Supuestos!C9)+B35 -> 2058.5175 | D35: =MAX(0,C35-Supuestos!C14)*Supuestos!C8 -> 111.51105 | E35: =Supuestos!C12*(1-Supuestos!C13*Supuestos!C15) -> 97.515 | F35: =D35*E35 -> 10874 | G35: =F35*12 -> 130488 | H35: =D35*Supuestos!C10 -> 2787.7762 | I35: =F35-H35 -> 8086.2236 | J35: =IF(F35=0,0,I35/F35) -> 0.74362919
A36: 31 | B36: =B35*(1+Supuestos!C7) -> 332.06768 | C36: =C35*(1-Supuestos!C9)+B36 -> 2225.9037 | D36: =MAX(0,C36-Supuestos!C14)*Supuestos!C8 -> 121.55422 | E36: =Supuestos!C12*(1-Supuestos!C13*Supuestos!C15) -> 97.515 | F36: =D36*E36 -> 11853.36 | G36: =F36*12 -> 142240.32 | H36: =D36*Supuestos!C10 -> 3038.8556 | I36: =F36-H36 -> 8814.5046 | J36: =IF(F36=0,0,I36/F36) -> 0.74362919
A37: 32 | B37: =B36*(1+Supuestos!C7) -> 358.63309 | C37: =C36*(1-Supuestos!C9)+B37 -> 2406.4645 | D37: =MAX(0,C37-Supuestos!C14)*Supuestos!C8 -> 132.38787 | E37: =Supuestos!C12*(1-Supuestos!C13*Supuestos!C15) -> 97.515 | F37: =D37*E37 -> 12909.803 | G37: =F37*12 -> 154917.64 | H37: =D37*Supuestos!C10 -> 3309.6968 | I37: =F37-H37 -> 9600.1065 | J37: =IF(F37=0,0,I37/F37) -> 0.74362919
A38: 33 | B38: =B37*(1+Supuestos!C7) -> 387.32374 | C38: =C37*(1-Supuestos!C9)+B38 -> 2601.2711 | D38: =MAX(0,C38-Supuestos!C14)*Supuestos!C8 -> 144.07627 | E38: =Supuestos!C12*(1-Supuestos!C13*Supuestos!C15) -> 97.515 | F38: =D38*E38 -> 14049.597 | G38: =F38*12 -> 168595.17 | H38: =D38*Supuestos!C10 -> 3601.9067 | I38: =F38-H38 -> 10447.69 | J38: =IF(F38=0,0,I38/F38) -> 0.74362919
A39: 34 | B39: =B38*(1+Supuestos!C7) -> 418.30964 | C39: =C38*(1-Supuestos!C9)+B39 -> 2811.4791 | D39: =MAX(0,C39-Supuestos!C14)*Supuestos!C8 -> 156.68874 | E39: =Supuestos!C12*(1-Supuestos!C13*Supuestos!C15) -> 97.515 | F39: =D39*E39 -> 15279.503 | G39: =F39*12 -> 183354.03 | H39: =D39*Supuestos!C10 -> 3917.2186 | I39: =F39-H39 -> 11362.284 | J39: =IF(F39=0,0,I39/F39) -> 0.74362919
A40: 35 | B40: =B39*(1+Supuestos!C7) -> 451.77441 | C40: =C39*(1-Supuestos!C9)+B40 -> 3038.3351 | D40: =MAX(0,C40-Supuestos!C14)*Supuestos!C8 -> 170.30011 | E40: =Supuestos!C12*(1-Supuestos!C13*Supuestos!C15) -> 97.515 | F40: =D40*E40 -> 16606.815 | G40: =F40*12 -> 199281.78 | H40: =D40*Supuestos!C10 -> 4257.5027 | I40: =F40-H40 -> 12349.312 | J40: =IF(F40=0,0,I40/F40) -> 0.74362919
A41: 36 | B41: =B40*(1+Supuestos!C7) -> 487.91636 | C41: =C40*(1-Supuestos!C9)+B41 -> 3283.1847 | D41: =MAX(0,C41-Supuestos!C14)*Supuestos!C8 -> 184.99108 | E41: =Supuestos!C12*(1-Supuestos!C13*Supuestos!C15) -> 97.515 | F41: =D41*E41 -> 18039.405 | G41: =F41*12 -> 216472.86 | H41: =D41*Supuestos!C10 -> 4624.777 | I41: =F41-H41 -> 13414.628 | J41: =IF(F41=0,0,I41/F41) -> 0.74362919
A43: Escenario: Base
A44: Mes | B44: Nuevos duos | C44: Duos activos | D44: Duos de pago | E44: ARPU efectivo | F44: MRR | G44: ARR | H44: Costo var. total | I44: Margen bruto | J44: Margen %
A45: 1 | B45: =Supuestos!D6 -> 47 | C45: =B45 -> 47 | D45: =MAX(0,C45-Supuestos!D14)*Supuestos!D8 -> 0 | E45: =Supuestos!D12*(1-Supuestos!D13*Supuestos!D15) -> 96.03 | F45: =D45*E45 -> 0 | G45: =F45*12 -> 0 | H45: =D45*Supuestos!D10 -> 0 | I45: =F45-H45 -> 0 | J45: =IF(F45=0,0,I45/F45) -> 0
A46: 2 | B46: =B45*(1+Supuestos!D7) -> 51.7 | C46: =C45*(1-Supuestos!D9)+B46 -> 96.35 | D46: =MAX(0,C46-Supuestos!D14)*Supuestos!D8 -> 0 | E46: =Supuestos!D12*(1-Supuestos!D13*Supuestos!D15) -> 96.03 | F46: =D46*E46 -> 0 | G46: =F46*12 -> 0 | H46: =D46*Supuestos!D10 -> 0 | I46: =F46-H46 -> 0 | J46: =IF(F46=0,0,I46/F46) -> 0
A47: 3 | B47: =B46*(1+Supuestos!D7) -> 56.87 | C47: =C46*(1-Supuestos!D9)+B47 -> 148.4025 | D47: =MAX(0,C47-Supuestos!D14)*Supuestos!D8 -> 0 | E47: =Supuestos!D12*(1-Supuestos!D13*Supuestos!D15) -> 96.03 | F47: =D47*E47 -> 0 | G47: =F47*12 -> 0 | H47: =D47*Supuestos!D10 -> 0 | I47: =F47-H47 -> 0 | J47: =IF(F47=0,0,I47/F47) -> 0
A48: 4 | B48: =B47*(1+Supuestos!D7) -> 62.557 | C48: =C47*(1-Supuestos!D9)+B48 -> 203.53937 | D48: =MAX(0,C48-Supuestos!D14)*Supuestos!D8 -> 0.424725 | E48: =Supuestos!D12*(1-Supuestos!D13*Supuestos!D15) -> 96.03 | F48: =D48*E48 -> 40.786342 | G48: =F48*12 -> 489.4361 | H48: =D48*Supuestos!D10 -> 8.4945 | I48: =F48-H48 -> 32.291842 | J48: =IF(F48=0,0,I48/F48) -> 0.79173175
A49: 5 | B49: =B48*(1+Supuestos!D7) -> 68.8127 | C49: =C48*(1-Supuestos!D9)+B49 -> 262.17511 | D49: =MAX(0,C49-Supuestos!D14)*Supuestos!D8 -> 7.4610127 | E49: =Supuestos!D12*(1-Supuestos!D13*Supuestos!D15) -> 96.03 | F49: =D49*E49 -> 716.48105 | G49: =F49*12 -> 8597.7727 | H49: =D49*Supuestos!D10 -> 149.22025 | I49: =F49-H49 -> 567.2608 | J49: =IF(F49=0,0,I49/F49) -> 0.79173175
A50: 6 | B50: =B49*(1+Supuestos!D7) -> 75.69397 | C50: =C49*(1-Supuestos!D9)+B50 -> 324.76032 | D50: =MAX(0,C50-Supuestos!D14)*Supuestos!D8 -> 14.971239 | E50: =Supuestos!D12*(1-Supuestos!D13*Supuestos!D15) -> 96.03 | F50: =D50*E50 -> 1437.688 | G50: =F50*12 -> 17252.256 | H50: =D50*Supuestos!D10 -> 299.42477 | I50: =F50-H50 -> 1138.2633 | J50: =IF(F50=0,0,I50/F50) -> 0.79173175
A51: 7 | B51: =B50*(1+Supuestos!D7) -> 83.263367 | C51: =C50*(1-Supuestos!D9)+B51 -> 391.78567 | D51: =MAX(0,C51-Supuestos!D14)*Supuestos!D8 -> 23.014281 | E51: =Supuestos!D12*(1-Supuestos!D13*Supuestos!D15) -> 96.03 | F51: =D51*E51 -> 2210.0614 | G51: =F51*12 -> 26520.736 | H51: =D51*Supuestos!D10 -> 460.28561 | I51: =F51-H51 -> 1749.7758 | J51: =IF(F51=0,0,I51/F51) -> 0.79173175
A52: 8 | B52: =B51*(1+Supuestos!D7) -> 91.589704 | C52: =C51*(1-Supuestos!D9)+B52 -> 463.78609 | D52: =MAX(0,C52-Supuestos!D14)*Supuestos!D8 -> 31.654331 | E52: =Supuestos!D12*(1-Supuestos!D13*Supuestos!D15) -> 96.03 | F52: =D52*E52 -> 3039.7654 | G52: =F52*12 -> 36477.185 | H52: =D52*Supuestos!D10 -> 633.08662 | I52: =F52-H52 -> 2406.6788 | J52: =IF(F52=0,0,I52/F52) -> 0.79173175
A53: 9 | B53: =B52*(1+Supuestos!D7) -> 100.74867 | C53: =C52*(1-Supuestos!D9)+B53 -> 541.34546 | D53: =MAX(0,C53-Supuestos!D14)*Supuestos!D8 -> 40.961455 | E53: =Supuestos!D12*(1-Supuestos!D13*Supuestos!D15) -> 96.03 | F53: =D53*E53 -> 3933.5286 | G53: =F53*12 -> 47202.343 | H53: =D53*Supuestos!D10 -> 819.22911 | I53: =F53-H53 -> 3114.2995 | J53: =IF(F53=0,0,I53/F53) -> 0.79173175
A54: 10 | B54: =B53*(1+Supuestos!D7) -> 110.82354 | C54: =C53*(1-Supuestos!D9)+B54 -> 625.10173 | D54: =MAX(0,C54-Supuestos!D14)*Supuestos!D8 -> 51.012208 | E54: =Supuestos!D12*(1-Supuestos!D13*Supuestos!D15) -> 96.03 | F54: =D54*E54 -> 4898.7023 | G54: =F54*12 -> 58784.428 | H54: =D54*Supuestos!D10 -> 1020.2442 | I54: =F54-H54 -> 3878.4581 | J54: =IF(F54=0,0,I54/F54) -> 0.79173175
A55: 11 | B55: =B54*(1+Supuestos!D7) -> 121.9059 | C55: =C54*(1-Supuestos!D9)+B55 -> 715.75254 | D55: =MAX(0,C55-Supuestos!D14)*Supuestos!D8 -> 61.890305 | E55: =Supuestos!D12*(1-Supuestos!D13*Supuestos!D15) -> 96.03 | F55: =D55*E55 -> 5943.326 | G55: =F55*12 -> 71319.912 | H55: =D55*Supuestos!D10 -> 1237.8061 | I55: =F55-H55 -> 4705.5199 | J55: =IF(F55=0,0,I55/F55) -> 0.79173175
A56: 12 | B56: =B55*(1+Supuestos!D7) -> 134.09649 | C56: =C55*(1-Supuestos!D9)+B56 -> 814.0614 | D56: =MAX(0,C56-Supuestos!D14)*Supuestos!D8 -> 73.687368 | E56: =Supuestos!D12*(1-Supuestos!D13*Supuestos!D15) -> 96.03 | F56: =D56*E56 -> 7076.1979 | G56: =F56*12 -> 84914.375 | H56: =D56*Supuestos!D10 -> 1473.7474 | I56: =F56-H56 -> 5602.4506 | J56: =IF(F56=0,0,I56/F56) -> 0.79173175
A57: 13 | B57: =B56*(1+Supuestos!D7) -> 147.50613 | C57: =C56*(1-Supuestos!D9)+B57 -> 920.86446 | D57: =MAX(0,C57-Supuestos!D14)*Supuestos!D8 -> 86.503735 | E57: =Supuestos!D12*(1-Supuestos!D13*Supuestos!D15) -> 96.03 | F57: =D57*E57 -> 8306.9537 | G57: =F57*12 -> 99683.444 | H57: =D57*Supuestos!D10 -> 1730.0747 | I57: =F57-H57 -> 6576.879 | J57: =IF(F57=0,0,I57/F57) -> 0.79173175
A58: 14 | B58: =B57*(1+Supuestos!D7) -> 162.25675 | C58: =C57*(1-Supuestos!D9)+B58 -> 1037.078 | D58: =MAX(0,C58-Supuestos!D14)*Supuestos!D8 -> 100.44936 | E58: =Supuestos!D12*(1-Supuestos!D13*Supuestos!D15) -> 96.03 | F58: =D58*E58 -> 9646.1519 | G58: =F58*12 -> 115753.82 | H58: =D58*Supuestos!D10 -> 2008.9872 | I58: =F58-H58 -> 7637.1647 | J58: =IF(F58=0,0,I58/F58) -> 0.79173175
A59: 15 | B59: =B58*(1+Supuestos!D7) -> 178.48242 | C59: =C58*(1-Supuestos!D9)+B59 -> 1163.7065 | D59: =MAX(0,C59-Supuestos!D14)*Supuestos!D8 -> 115.64478 | E59: =Supuestos!D12*(1-Supuestos!D13*Supuestos!D15) -> 96.03 | F59: =D59*E59 -> 11105.368 | G59: =F59*12 -> 133264.42 | H59: =D59*Supuestos!D10 -> 2312.8956 | I59: =F59-H59 -> 8792.4727 | J59: =IF(F59=0,0,I59/F59) -> 0.79173175
A60: 16 | B60: =B59*(1+Supuestos!D7) -> 196.33066 | C60: =C59*(1-Supuestos!D9)+B60 -> 1301.8518 | D60: =MAX(0,C60-Supuestos!D14)*Supuestos!D8 -> 132.22222 | E60: =Supuestos!D12*(1-Supuestos!D13*Supuestos!D15) -> 96.03 | F60: =D60*E60 -> 12697.3 | G60: =F60*12 -> 152367.6 | H60: =D60*Supuestos!D10 -> 2644.4444 | I60: =F60-H60 -> 10052.856 | J60: =IF(F60=0,0,I60/F60) -> 0.79173175
A61: 17 | B61: =B60*(1+Supuestos!D7) -> 215.96373 | C61: =C60*(1-Supuestos!D9)+B61 -> 1452.723 | D61: =MAX(0,C61-Supuestos!D14)*Supuestos!D8 -> 150.32676 | E61: =Supuestos!D12*(1-Supuestos!D13*Supuestos!D15) -> 96.03 | F61: =D61*E61 -> 14435.879 | G61: =F61*12 -> 173230.54 | H61: =D61*Supuestos!D10 -> 3006.5352 | I61: =F61-H61 -> 11429.343 | J61: =IF(F61=0,0,I61/F61) -> 0.79173175
A62: 18 | B62: =B61*(1+Supuestos!D7) -> 237.5601 | C62: =C61*(1-Supuestos!D9)+B62 -> 1617.6469 | D62: =MAX(0,C62-Supuestos!D14)*Supuestos!D8 -> 170.11763 | E62: =Supuestos!D12*(1-Supuestos!D13*Supuestos!D15) -> 96.03 | F62: =D62*E62 -> 16336.396 | G62: =F62*12 -> 196036.76 | H62: =D62*Supuestos!D10 -> 3402.3527 | I62: =F62-H62 -> 12934.044 | J62: =IF(F62=0,0,I62/F62) -> 0.79173175
A63: 19 | B63: =B62*(1+Supuestos!D7) -> 261.31611 | C63: =C62*(1-Supuestos!D9)+B63 -> 1798.0807 | D63: =MAX(0,C63-Supuestos!D14)*Supuestos!D8 -> 191.76968 | E63: =Supuestos!D12*(1-Supuestos!D13*Supuestos!D15) -> 96.03 | F63: =D63*E63 -> 18415.643 | G63: =F63*12 -> 220987.71 | H63: =D63*Supuestos!D10 -> 3835.3937 | I63: =F63-H63 -> 14580.249 | J63: =IF(F63=0,0,I63/F63) -> 0.79173175
A64: 20 | B64: =B63*(1+Supuestos!D7) -> 287.44773 | C64: =C63*(1-Supuestos!D9)+B64 -> 1995.6244 | D64: =MAX(0,C64-Supuestos!D14)*Supuestos!D8 -> 215.47493 | E64: =Supuestos!D12*(1-Supuestos!D13*Supuestos!D15) -> 96.03 | F64: =D64*E64 -> 20692.057 | G64: =F64*12 -> 248304.69 | H64: =D64*Supuestos!D10 -> 4309.4985 | I64: =F64-H64 -> 16382.559 | J64: =IF(F64=0,0,I64/F64) -> 0.79173175
A65: 21 | B65: =B64*(1+Supuestos!D7) -> 316.1925 | C65: =C64*(1-Supuestos!D9)+B65 -> 2212.0357 | D65: =MAX(0,C65-Supuestos!D14)*Supuestos!D8 -> 241.44428 | E65: =Supuestos!D12*(1-Supuestos!D13*Supuestos!D15) -> 96.03 | F65: =D65*E65 -> 23185.894 | G65: =F65*12 -> 278230.73 | H65: =D65*Supuestos!D10 -> 4828.8856 | I65: =F65-H65 -> 18357.009 | J65: =IF(F65=0,0,I65/F65) -> 0.79173175
A66: 22 | B66: =B65*(1+Supuestos!D7) -> 347.81175 | C66: =C65*(1-Supuestos!D9)+B66 -> 2449.2456 | D66: =MAX(0,C66-Supuestos!D14)*Supuestos!D8 -> 269.90948 | E66: =Supuestos!D12*(1-Supuestos!D13*Supuestos!D15) -> 96.03 | F66: =D66*E66 -> 25919.407 | G66: =F66*12 -> 311032.88 | H66: =D66*Supuestos!D10 -> 5398.1895 | I66: =F66-H66 -> 20521.217 | J66: =IF(F66=0,0,I66/F66) -> 0.79173175
A67: 23 | B67: =B66*(1+Supuestos!D7) -> 382.59292 | C67: =C66*(1-Supuestos!D9)+B67 -> 2709.3763 | D67: =MAX(0,C67-Supuestos!D14)*Supuestos!D8 -> 301.12515 | E67: =Supuestos!D12*(1-Supuestos!D13*Supuestos!D15) -> 96.03 | F67: =D67*E67 -> 28917.048 | G67: =F67*12 -> 347004.58 | H67: =D67*Supuestos!D10 -> 6022.5031 | I67: =F67-H67 -> 22894.545 | J67: =IF(F67=0,0,I67/F67) -> 0.79173175
A68: 24 | B68: =B67*(1+Supuestos!D7) -> 420.85221 | C68: =C67*(1-Supuestos!D9)+B68 -> 2994.7597 | D68: =MAX(0,C68-Supuestos!D14)*Supuestos!D8 -> 335.37116 | E68: =Supuestos!D12*(1-Supuestos!D13*Supuestos!D15) -> 96.03 | F68: =D68*E68 -> 32205.693 | G68: =F68*12 -> 386468.31 | H68: =D68*Supuestos!D10 -> 6707.4232 | I68: =F68-H68 -> 25498.269 | J68: =IF(F68=0,0,I68/F68) -> 0.79173175
A69: 25 | B69: =B68*(1+Supuestos!D7) -> 462.93744 | C69: =C68*(1-Supuestos!D9)+B69 -> 3307.9591 | D69: =MAX(0,C69-Supuestos!D14)*Supuestos!D8 -> 372.9551 | E69: =Supuestos!D12*(1-Supuestos!D13*Supuestos!D15) -> 96.03 | F69: =D69*E69 -> 35814.878 | G69: =F69*12 -> 429778.53 | H69: =D69*Supuestos!D10 -> 7459.1019 | I69: =F69-H69 -> 28355.776 | J69: =IF(F69=0,0,I69/F69) -> 0.79173175
A70: 26 | B70: =B69*(1+Supuestos!D7) -> 509.23118 | C70: =C69*(1-Supuestos!D9)+B70 -> 3651.7924 | D70: =MAX(0,C70-Supuestos!D14)*Supuestos!D8 -> 414.21508 | E70: =Supuestos!D12*(1-Supuestos!D13*Supuestos!D15) -> 96.03 | F70: =D70*E70 -> 39777.074 | G70: =F70*12 -> 477324.89 | H70: =D70*Supuestos!D10 -> 8284.3016 | I70: =F70-H70 -> 31492.773 | J70: =IF(F70=0,0,I70/F70) -> 0.79173175
A71: 27 | B71: =B70*(1+Supuestos!D7) -> 560.1543 | C71: =C70*(1-Supuestos!D9)+B71 -> 4029.357 | D71: =MAX(0,C71-Supuestos!D14)*Supuestos!D8 -> 459.52284 | E71: =Supuestos!D12*(1-Supuestos!D13*Supuestos!D15) -> 96.03 | F71: =D71*E71 -> 44127.979 | G71: =F71*12 -> 529535.74 | H71: =D71*Supuestos!D10 -> 9190.4569 | I71: =F71-H71 -> 34937.522 | J71: =IF(F71=0,0,I71/F71) -> 0.79173175
A72: 28 | B72: =B71*(1+Supuestos!D7) -> 616.16973 | C72: =C71*(1-Supuestos!D9)+B72 -> 4444.0589 | D72: =MAX(0,C72-Supuestos!D14)*Supuestos!D8 -> 509.28707 | E72: =Supuestos!D12*(1-Supuestos!D13*Supuestos!D15) -> 96.03 | F72: =D72*E72 -> 48906.837 | G72: =F72*12 -> 586882.05 | H72: =D72*Supuestos!D10 -> 10185.741 | I72: =F72-H72 -> 38721.096 | J72: =IF(F72=0,0,I72/F72) -> 0.79173175
A73: 29 | B73: =B72*(1+Supuestos!D7) -> 677.7867 | C73: =C72*(1-Supuestos!D9)+B73 -> 4899.6427 | D73: =MAX(0,C73-Supuestos!D14)*Supuestos!D8 -> 563.95712 | E73: =Supuestos!D12*(1-Supuestos!D13*Supuestos!D15) -> 96.03 | F73: =D73*E73 -> 54156.802 | G73: =F73*12 -> 649881.63 | H73: =D73*Supuestos!D10 -> 11279.142 | I73: =F73-H73 -> 42877.66 | J73: =IF(F73=0,0,I73/F73) -> 0.79173175
A74: 30 | B74: =B73*(1+Supuestos!D7) -> 745.56537 | C74: =C73*(1-Supuestos!D9)+B74 -> 5400.2259 | D74: =MAX(0,C74-Supuestos!D14)*Supuestos!D8 -> 624.02711 | E74: =Supuestos!D12*(1-Supuestos!D13*Supuestos!D15) -> 96.03 | F74: =D74*E74 -> 59925.323 | G74: =F74*12 -> 719103.88 | H74: =D74*Supuestos!D10 -> 12480.542 | I74: =F74-H74 -> 47444.781 | J74: =IF(F74=0,0,I74/F74) -> 0.79173175
A75: 31 | B75: =B74*(1+Supuestos!D7) -> 820.12191 | C75: =C74*(1-Supuestos!D9)+B75 -> 5950.3365 | D75: =MAX(0,C75-Supuestos!D14)*Supuestos!D8 -> 690.04038 | E75: =Supuestos!D12*(1-Supuestos!D13*Supuestos!D15) -> 96.03 | F75: =D75*E75 -> 66264.578 | G75: =F75*12 -> 795174.93 | H75: =D75*Supuestos!D10 -> 13800.808 | I75: =F75-H75 -> 52463.77 | J75: =IF(F75=0,0,I75/F75) -> 0.79173175
A76: 32 | B76: =B75*(1+Supuestos!D7) -> 902.1341 | C76: =C75*(1-Supuestos!D9)+B76 -> 6554.9538 | D76: =MAX(0,C76-Supuestos!D14)*Supuestos!D8 -> 762.59445 | E76: =Supuestos!D12*(1-Supuestos!D13*Supuestos!D15) -> 96.03 | F76: =D76*E76 -> 73231.945 | G76: =F76*12 -> 878783.34 | H76: =D76*Supuestos!D10 -> 15251.889 | I76: =F76-H76 -> 57980.056 | J76: =IF(F76=0,0,I76/F76) -> 0.79173175
A77: 33 | B77: =B76*(1+Supuestos!D7) -> 992.34751 | C77: =C76*(1-Supuestos!D9)+B77 -> 7219.5536 | D77: =MAX(0,C77-Supuestos!D14)*Supuestos!D8 -> 842.34643 | E77: =Supuestos!D12*(1-Supuestos!D13*Supuestos!D15) -> 96.03 | F77: =D77*E77 -> 80890.528 | G77: =F77*12 -> 970686.33 | H77: =D77*Supuestos!D10 -> 16846.929 | I77: =F77-H77 -> 64043.599 | J77: =IF(F77=0,0,I77/F77) -> 0.79173175
A78: 34 | B78: =B77*(1+Supuestos!D7) -> 1091.5823 | C78: =C77*(1-Supuestos!D9)+B78 -> 7950.1582 | D78: =MAX(0,C78-Supuestos!D14)*Supuestos!D8 -> 930.01898 | E78: =Supuestos!D12*(1-Supuestos!D13*Supuestos!D15) -> 96.03 | F78: =D78*E78 -> 89309.723 | G78: =F78*12 -> 1071716.7 | H78: =D78*Supuestos!D10 -> 18600.38 | I78: =F78-H78 -> 70709.343 | J78: =IF(F78=0,0,I78/F78) -> 0.79173175
A79: 35 | B79: =B78*(1+Supuestos!D7) -> 1200.7405 | C79: =C78*(1-Supuestos!D9)+B79 -> 8753.3908 | D79: =MAX(0,C79-Supuestos!D14)*Supuestos!D8 -> 1026.4069 | E79: =Supuestos!D12*(1-Supuestos!D13*Supuestos!D15) -> 96.03 | F79: =D79*E79 -> 98565.854 | G79: =F79*12 -> 1182790.2 | H79: =D79*Supuestos!D10 -> 20528.138 | I79: =F79-H79 -> 78037.716 | J79: =IF(F79=0,0,I79/F79) -> 0.79173175
A80: 36 | B80: =B79*(1+Supuestos!D7) -> 1320.8145 | C80: =C79*(1-Supuestos!D9)+B80 -> 9636.5357 | D80: =MAX(0,C80-Supuestos!D14)*Supuestos!D8 -> 1132.3843 | E80: =Supuestos!D12*(1-Supuestos!D13*Supuestos!D15) -> 96.03 | F80: =D80*E80 -> 108742.86 | G80: =F80*12 -> 1304914.4 | H80: =D80*Supuestos!D10 -> 22647.686 | I80: =F80-H80 -> 86095.178 | J80: =IF(F80=0,0,I80/F80) -> 0.79173175
A82: Escenario: Agresivo
A83: Mes | B83: Nuevos duos | C83: Duos activos | D83: Duos de pago | E83: ARPU efectivo | F83: MRR | G83: ARR | H83: Costo var. total | I83: Margen bruto | J83: Margen %
A84: 1 | B84: =Supuestos!E6 -> 87 | C84: =B84 -> 87 | D84: =MAX(0,C84-Supuestos!E14)*Supuestos!E8 -> 0 | E84: =Supuestos!E12*(1-Supuestos!E13*Supuestos!E15) -> 94.545 | F84: =D84*E84 -> 0 | G84: =F84*12 -> 0 | H84: =D84*Supuestos!E10 -> 0 | I84: =F84-H84 -> 0 | J84: =IF(F84=0,0,I84/F84) -> 0
A85: 2 | B85: =B84*(1+Supuestos!E7) -> 97.005 | C85: =C84*(1-Supuestos!E9)+B85 -> 180.96 | D85: =MAX(0,C85-Supuestos!E14)*Supuestos!E8 -> 0 | E85: =Supuestos!E12*(1-Supuestos!E13*Supuestos!E15) -> 94.545 | F85: =D85*E85 -> 0 | G85: =F85*12 -> 0 | H85: =D85*Supuestos!E10 -> 0 | I85: =F85-H85 -> 0 | J85: =IF(F85=0,0,I85/F85) -> 0
A86: 3 | B86: =B85*(1+Supuestos!E7) -> 108.16057 | C86: =C85*(1-Supuestos!E9)+B86 -> 282.78697 | D86: =MAX(0,C86-Supuestos!E14)*Supuestos!E8 -> 16.557395 | E86: =Supuestos!E12*(1-Supuestos!E13*Supuestos!E15) -> 94.545 | F86: =D86*E86 -> 1565.4189 | G86: =F86*12 -> 18785.027 | H86: =D86*Supuestos!E10 -> 248.36092 | I86: =F86-H86 -> 1317.058 | J86: =IF(F86=0,0,I86/F86) -> 0.84134539
A87: 4 | B87: =B86*(1+Supuestos!E7) -> 120.59904 | C87: =C86*(1-Supuestos!E9)+B87 -> 393.48847 | D87: =MAX(0,C87-Supuestos!E14)*Supuestos!E8 -> 38.697694 | E87: =Supuestos!E12*(1-Supuestos!E13*Supuestos!E15) -> 94.545 | F87: =D87*E87 -> 3658.6735 | G87: =F87*12 -> 43904.082 | H87: =D87*Supuestos!E10 -> 580.46542 | I87: =F87-H87 -> 3078.2081 | J87: =IF(F87=0,0,I87/F87) -> 0.84134539
A88: 5 | B88: =B87*(1+Supuestos!E7) -> 134.46793 | C88: =C87*(1-Supuestos!E9)+B88 -> 514.18431 | D88: =MAX(0,C88-Supuestos!E14)*Supuestos!E8 -> 62.836861 | E88: =Supuestos!E12*(1-Supuestos!E13*Supuestos!E15) -> 94.545 | F88: =D88*E88 -> 5940.911 | G88: =F88*12 -> 71290.933 | H88: =D88*Supuestos!E10 -> 942.55292 | I88: =F88-H88 -> 4998.3581 | J88: =IF(F88=0,0,I88/F88) -> 0.84134539
A89: 6 | B89: =B88*(1+Supuestos!E7) -> 149.93174 | C89: =C88*(1-Supuestos!E9)+B89 -> 646.1196 | D89: =MAX(0,C89-Supuestos!E14)*Supuestos!E8 -> 89.22392 | E89: =Supuestos!E12*(1-Supuestos!E13*Supuestos!E15) -> 94.545 | F89: =D89*E89 -> 8435.6755 | G89: =F89*12 -> 101228.11 | H89: =D89*Supuestos!E10 -> 1338.3588 | I89: =F89-H89 -> 7097.3167 | J89: =IF(F89=0,0,I89/F89) -> 0.84134539
A90: 7 | B90: =B89*(1+Supuestos!E7) -> 167.17389 | C90: =C89*(1-Supuestos!E9)+B90 -> 790.67931 | D90: =MAX(0,C90-Supuestos!E14)*Supuestos!E8 -> 118.13586 | E90: =Supuestos!E12*(1-Supuestos!E13*Supuestos!E15) -> 94.545 | F90: =D90*E90 -> 11169.155 | G90: =F90*12 -> 134029.86 | H90: =D90*Supuestos!E10 -> 1772.0379 | I90: =F90-H90 -> 9397.1171 | J90: =IF(F90=0,0,I90/F90) -> 0.84134539
A91: 8 | B91: =B90*(1+Supuestos!E7) -> 186.39889 | C91: =C90*(1-Supuestos!E9)+B91 -> 949.40442 | D91: =MAX(0,C91-Supuestos!E14)*Supuestos!E8 -> 149.88088 | E91: =Supuestos!E12*(1-Supuestos!E13*Supuestos!E15) -> 94.545 | F91: =D91*E91 -> 14170.488 | G91: =F91*12 -> 170045.86 | H91: =D91*Supuestos!E10 -> 2248.2133 | I91: =F91-H91 -> 11922.275 | J91: =IF(F91=0,0,I91/F91) -> 0.84134539
A92: 9 | B92: =B91*(1+Supuestos!E7) -> 207.83476 | C92: =C91*(1-Supuestos!E9)+B92 -> 1124.01 | D92: =MAX(0,C92-Supuestos!E14)*Supuestos!E8 -> 184.80201 | E92: =Supuestos!E12*(1-Supuestos!E13*Supuestos!E15) -> 94.545 | F92: =D92*E92 -> 17472.106 | G92: =F92*12 -> 209665.27 | H92: =D92*Supuestos!E10 -> 2772.0301 | I92: =F92-H92 -> 14700.076 | J92: =IF(F92=0,0,I92/F92) -> 0.84134539
A93: 10 | B93: =B92*(1+Supuestos!E7) -> 231.73576 | C93: =C92*(1-Supuestos!E9)+B93 -> 1316.4054 | D93: =MAX(0,C93-Supuestos!E14)*Supuestos!E8 -> 223.28109 | E93: =Supuestos!E12*(1-Supuestos!E13*Supuestos!E15) -> 94.545 | F93: =D93*E93 -> 21110.11 | G93: =F93*12 -> 253321.33 | H93: =D93*Supuestos!E10 -> 3349.2163 | I93: =F93-H93 -> 17760.894 | J93: =IF(F93=0,0,I93/F93) -> 0.84134539
A94: 11 | B94: =B93*(1+Supuestos!E7) -> 258.38537 | C94: =C93*(1-Supuestos!E9)+B94 -> 1528.7166 | D94: =MAX(0,C94-Supuestos!E14)*Supuestos!E8 -> 265.74332 | E94: =Supuestos!E12*(1-Supuestos!E13*Supuestos!E15) -> 94.545 | F94: =D94*E94 -> 25124.703 | G94: =F94*12 -> 301496.43 | H94: =D94*Supuestos!E10 -> 3986.1499 | I94: =F94-H94 -> 21138.553 | J94: =IF(F94=0,0,I94/F94) -> 0.84134539
A95: 12 | B95: =B94*(1+Supuestos!E7) -> 288.09969 | C95: =C94*(1-Supuestos!E9)+B95 -> 1763.3112 | D95: =MAX(0,C95-Supuestos!E14)*Supuestos!E8 -> 312.66225 | E95: =Supuestos!E12*(1-Supuestos!E13*Supuestos!E15) -> 94.545 | F95: =D95*E95 -> 29560.652 | G95: =F95*12 -> 354727.83 | H95: =D95*Supuestos!E10 -> 4689.9337 | I95: =F95-H95 -> 24870.718 | J95: =IF(F95=0,0,I95/F95) -> 0.84134539
A96: 13 | B96: =B95*(1+Supuestos!E7) -> 321.23116 | C96: =C95*(1-Supuestos!E9)+B96 -> 2022.8265 | D96: =MAX(0,C96-Supuestos!E14)*Supuestos!E8 -> 364.5653 | E96: =Supuestos!E12*(1-Supuestos!E13*Supuestos!E15) -> 94.545 | F96: =D96*E96 -> 34467.826 | G96: =F96*12 -> 413613.91 | H96: =D96*Supuestos!E10 -> 5468.4795 | I96: =F96-H96 -> 28999.347 | J96: =IF(F96=0,0,I96/F96) -> 0.84134539
A97: 14 | B97: =B96*(1+Supuestos!E7) -> 358.17274 | C97: =C96*(1-Supuestos!E9)+B97 -> 2310.2003 | D97: =MAX(0,C97-Supuestos!E14)*Supuestos!E8 -> 422.04006 | E97: =Supuestos!E12*(1-Supuestos!E13*Supuestos!E15) -> 94.545 | F97: =D97*E97 -> 39901.778 | G97: =F97*12 -> 478821.33 | H97: =D97*Supuestos!E10 -> 6330.6009 | I97: =F97-H97 -> 33571.177 | J97: =IF(F97=0,0,I97/F97) -> 0.84134539
A98: 15 | B98: =B97*(1+Supuestos!E7) -> 399.3626 | C98: =C97*(1-Supuestos!E9)+B98 -> 2628.7059 | D98: =MAX(0,C98-Supuestos!E14)*Supuestos!E8 -> 485.74118 | E98: =Supuestos!E12*(1-Supuestos!E13*Supuestos!E15) -> 94.545 | F98: =D98*E98 -> 45924.4 | G98: =F98*12 -> 551092.8 | H98: =D98*Supuestos!E10 -> 7286.1177 | I98: =F98-H98 -> 38638.282 | J98: =IF(F98=0,0,I98/F98) -> 0.84134539
A99: 16 | B99: =B98*(1+Supuestos!E7) -> 445.2893 | C99: =C98*(1-Supuestos!E9)+B99 -> 2981.9905 | D99: =MAX(0,C99-Supuestos!E14)*Supuestos!E8 -> 556.3981 | E99: =Supuestos!E12*(1-Supuestos!E13*Supuestos!E15) -> 94.545 | F99: =D99*E99 -> 52604.658 | G99: =F99*12 -> 631255.9 | H99: =D99*Supuestos!E10 -> 8345.9715 | I99: =F99-H99 -> 44258.687 | J99: =IF(F99=0,0,I99/F99) -> 0.84134539
A100: 17 | B100: =B99*(1+Supuestos!E7) -> 496.49757 | C100: =C99*(1-Supuestos!E9)+B100 -> 3374.1184 | D100: =MAX(0,C100-Supuestos!E14)*Supuestos!E8 -> 634.82368 | E100: =Supuestos!E12*(1-Supuestos!E13*Supuestos!E15) -> 94.545 | F100: =D100*E100 -> 60019.405 | G100: =F100*12 -> 720232.86 | H100: =D100*Supuestos!E10 -> 9522.3552 | I100: =F100-H100 -> 50497.05 | J100: =IF(F100=0,0,I100/F100) -> 0.84134539
A101: 18 | B101: =B100*(1+Supuestos!E7) -> 553.59479 | C101: =C100*(1-Supuestos!E9)+B101 -> 3809.6191 | D101: =MAX(0,C101-Supuestos!E14)*Supuestos!E8 -> 721.92381 | E101: =Supuestos!E12*(1-Supuestos!E13*Supuestos!E15) -> 94.545 | F101: =D101*E101 -> 68254.287 | G101: =F101*12 -> 819051.44 | H101: =D101*Supuestos!E10 -> 10828.857 | I101: =F101-H101 -> 57425.43 | J101: =IF(F101=0,0,I101/F101) -> 0.84134539
A102: 19 | B102: =B101*(1+Supuestos!E7) -> 617.2582 | C102: =C101*(1-Supuestos!E9)+B102 -> 4293.5406 | D102: =MAX(0,C102-Supuestos!E14)*Supuestos!E8 -> 818.70812 | E102: =Supuestos!E12*(1-Supuestos!E13*Supuestos!E15) -> 94.545 | F102: =D102*E102 -> 77404.759 | G102: =F102*12 -> 928857.11 | H102: =D102*Supuestos!E10 -> 12280.622 | I102: =F102-H102 -> 65124.137 | J102: =IF(F102=0,0,I102/F102) -> 0.84134539
A103: 20 | B103: =B102*(1+Supuestos!E7) -> 688.24289 | C103: =C102*(1-Supuestos!E9)+B103 -> 4831.5096 | D103: =MAX(0,C103-Supuestos!E14)*Supuestos!E8 -> 926.30191 | E103: =Supuestos!E12*(1-Supuestos!E13*Supuestos!E15) -> 94.545 | F103: =D103*E103 -> 87577.214 | G103: =F103*12 -> 1050926.6 | H103: =D103*Supuestos!E10 -> 13894.529 | I103: =F103-H103 -> 73682.686 | J103: =IF(F103=0,0,I103/F103) -> 0.84134539
...

Sheet Unit Economics
B2: Unit Economics por escenario
B3: LTV = (ARPU_ef * margen%) / churn. Payback = CAC / (ARPU_ef * margen%). Margen% en estado estable (M36).
B5: Metrica | C5: Conservador | D5: Base | E5: Agresivo
B6: ARPU efectivo (MXN/mes) | C6: =Proyeccion!E41 -> 97.515 | D6: =Proyeccion!E80 -> 96.03 | E6: =Proyeccion!E119 -> 94.545
B7: Margen bruto % | C7: =Proyeccion!J41 -> 0.74362919 | D7: =Proyeccion!J80 -> 0.79173175 | E7: =Proyeccion!J119 -> 0.84134539
B8: Churn mensual | C8: =Supuestos!C9 -> 0.08 | D8: =Supuestos!D9 -> 0.05 | E8: =Supuestos!E9 -> 0.035
B9: Contribucion / duo / mes | C9: =C6*C7 -> 72.515 | D9: =D6*D7 -> 76.03 | E9: =E6*E7 -> 79.545
B10: CAC por duo (MXN) | C10: =Supuestos!C11 -> 350 | D10: =Supuestos!D11 -> 250 | E10: =Supuestos!E11 -> 180
B11: LTV (MXN) | C11: =C9/C8 -> 906.4375 | D11: =D9/D8 -> 1520.6 | E11: =E9/E8 -> 2272.7143
B12: LTV : CAC | C12: =C11/C10 -> 2.5898214 | D12: =D11/D10 -> 6.0824 | E12: =E11/E10 -> 12.62619
B13: Payback (meses) | C13: =C10/C9 -> 4.8265876 | D13: =D10/D9 -> 3.2881757 | E13: =E10/E9 -> 2.2628701
B15: Base esperado: LTV ~$1,512 MXN, LTV:CAC ~6.0x, payback ~3.3 meses. La sensibilidad mas fuerte es el churn.
B17: Sensibilidad: LTV (Base) vs churn mensual
B18: Churn mensual | C18: LTV (MXN)
B19: 0.12 | C19: =D9/B19 -> 633.58333 | E19: Misma contribucion/duo del escenario Base; solo cambia el churn. Bajar churn de 12% a 5% mas que duplica el LTV.
B20: 0.08 | C20: =D9/B20 -> 950.375
B21: 0.06 | C21: =D9/B21 -> 1267.1667
B22: 0.05 | C22: =D9/B22 -> 1520.6
B23: 0.04 | C23: =D9/B23 -> 1900.75
B24: 0.035 | C24: =D9/B24 -> 2172.2857

Sheet Mercado
B2: Mercado Mexico [SUPUESTOS]
B3: Cifras de mercado son SUPUESTOS pre-seed con fines de dimensionamiento, no proyecciones. Unidad = DUO (2 personas).
B5: Nivel | C5: Duos | D5: Personas (~x2)
B6: TAM (total) | C6: 4500000 | D6: =C6*2 -> 9000000 | F6: Total de duos fitness potenciales en MX (~8-10M personas activas)
B7: SAM (alcanzable) | C7: 875000 | D7: =C7*2 -> 1750000 | F7: Segmento alcanzable: smartphone + intencion de entrenar en pareja/duo
B8: SOM 36m (objetivo) | C8: 15000 | D8: =C8*2 -> 30000 | F8: Captura realista a 36 meses (rango 5K-25K duos)
B10: SOM / SAM | C10: =C8/C7 -> 0.017142857
B11: SAM / TAM | C11: =C7/C6 -> 0.19444444
B12: SOM (duos) Base @ M36 | C12: =Proyeccion!C80 -> 9636.5357 | F12: Duos activos del escenario Base en M36 (link a Proyeccion) para comparar vs SOM supuesto.
B14: Rangos de referencia: TAM ~4-5M duos | SAM ~750K-1M duos | SOM 36m ~5K-25K duos. Ajustables arriba.

Sheet Hitos
B2: Hitos de MRR / ARR por escenario
B3: Todo referencia la hoja Proyeccion (links verdes). Cambia Supuestos y los hitos se mueven.
B4: Hito | C4: Conservador | D4: Base | E4: Agresivo
B5: MRR M12 | C5: =Proyeccion!F17 -> 1424.9363 | D5: =Proyeccion!F56 -> 7076.1979 | E5: =Proyeccion!F95 -> 29560.652 | G5: Guia objetivo: MRR M12 ~1.4K / 6.9K / 26.8K
B6: MRR M24 | C6: =Proyeccion!F29 -> 6318.9015 | D6: =Proyeccion!F68 -> 32205.693 | E6: =Proyeccion!F107 -> 141072.23 | G6: MRR M24 ~6.3K / 36.7K / 182K
B7: MRR M36 | C7: =Proyeccion!F41 -> 18039.405 | D7: =Proyeccion!F80 -> 108742.86 | E7: =Proyeccion!F119 -> 545243.75 | G7: MRR M36 ~17.2K / 109K / 478K
B8: ARR M36 | C8: =Proyeccion!G41 -> 216472.86 | D8: =Proyeccion!G80 -> 1304914.4 | E8: =Proyeccion!G119 -> 6542925 | G8: ARR M36 ~207K / 1.31M / 5.74M
B11: Duos de pago por hito
B12: Hito | C12: Conservador | D12: Base | E12: Agresivo
B13: Duos pago M12 | C13: =Proyeccion!D17 -> 14.612484 | D13: =Proyeccion!D56 -> 73.687368 | E13: =Proyeccion!D95 -> 312.66225
B14: Duos pago M24 | C14: =Proyeccion!D29 -> 64.799277 | D14: =Proyeccion!D68 -> 335.37116 | E14: =Proyeccion!D107 -> 1492.1173
B15: Duos pago M36 | C15: =Proyeccion!D41 -> 184.99108 | D15: =Proyeccion!D80 -> 1132.3843 | E15: =Proyeccion!D119 -> 5767.0289
